cscs_tools/__init__.py
cscs_tools/logger/__init__.py
cscs_tools/logger/services/__init__.py
cscs_tools/logger/services/logger_service.py
cscs_tools/version/__init__.py
cscs_tools/version/models/__init__.py
cscs_tools/version/models/entities/__init__.py
cscs_tools/version/models/entities/version.py
cscs_tools/version/repositories/__init__.py
cscs_tools/version/repositories/version_file_repository.py
cscs_tools/version/services/__init__.py
cscs_tools/version/services/version_service.py
cscs_tools-0.0.5.dist-info/licenses/LICENSE
cscs_tools-0.0.5.dist-info/METADATA
cscs_tools-0.0.5.dist-info/WHEEL
cscs_tools-0.0.5.dist-info/top_level.txt
cscs_tools-0.0.5.dist-info/RECORD
