Metadata-Version: 2.4
Name: cscs-tools
Version: 0.0.5
Summary: Utilities library
Author: Csaba Cselko
Author-email: Csaba Cselko <lendoo73dev@gmail.com>
License: MIT
Project-URL: Homepage, https://github.com/lendoo73/cscs-tools
Project-URL: Repository, https://github.com/lendoo73/cscs-tools
Project-URL: Issues, https://github.com/lendoo73/cscs-tools/issues
Classifier: Programming Language :: Python :: 3
Classifier: License :: OSI Approved :: MIT License
Requires-Python: >=3.8
License-File: LICENSE
Dynamic: author
Dynamic: license-file
Dynamic: requires-python
